slowstack/__init__.py
slowstack/asynchronous/all.py
slowstack/asynchronous/any.py
slowstack/asynchronous/base.py
slowstack/asynchronous/times_per.py
slowstack/asynchronous/utils/priority_queue_container.py
slowstack/asynchronous/utils/safe_cancel.py
slowstack/common/errors.py
slowstack/common/status.py
slowstack/synchronous/base.py
slowstack/synchronous/times_per.py
slowstack/synchronous/utils/priority_queue_container.py
slowstack_plus-1.0.0.dist-info/LICENSE
slowstack_plus-1.0.0.dist-info/METADATA
slowstack_plus-1.0.0.dist-info/WHEEL
slowstack_plus-1.0.0.dist-info/RECORD
