Metadata-Version: 2.1
Name: slowstack-plus
Version: 1.0.0
Summary: Epic's Slowstack lib but with python 3.8+ support.
Requires-Python: >=3.8
Classifier: Programming Language :: Python :: 3
Classifier: Programming Language :: Python :: 3.8
Classifier: Programming Language :: Python :: 3.9
Classifier: Programming Language :: Python :: 3.10
Classifier: Programming Language :: Python :: 3.11
Classifier: Programming Language :: Python :: 3.12
Requires-Dist: exceptiongroup (>=1.2.2,<2.0.0)
